<annotation>
	<folder>C:\Users\Asus\Desktop\train_polygon</folder>
	<filename>1680947903424.jpg</filename>
	<path>C:\Users\Asus\Desktop\train_polygon\1680947903424.jpg</path>
	<source>
		<database>Unknown</database>
		<annotation>Unknown</annotation>
		<image>Unknown</image>
	</source>
	<size>
		<width>930</width>
		<height>530</height>
		<depth>3</depth>
	</size>
	<segmented>0</segmented>
	<object>
		<name>nesne</name>
		<occluded>0</occluded>
		<pose>Unspecified</pose>
		<truncated>0</truncated>
		<difficult>0</difficult>
		<polygon>
			<x1>130</x1>
			<y1>284</y1>
			<x2>137</x2>
			<y2>275</y2>
			<x3>148</x3>
			<y3>275</y3>
			<x4>160</x4>
			<y4>277</y4>
			<x5>172</x5>
			<y5>281</y5>
			<x6>172</x6>
			<y6>285</y6>
			<x7>130</x7>
			<y7>284</y7>
		</polygon>
		<bndbox>
			<xmin>130</xmin>
			<ymin>275</ymin>
			<xmax>172</xmax>
			<ymax>285</ymax>
		</bndbox>
	</object>
	<object>
		<name>nesne</name>
		<occluded>0</occluded>
		<pose>Unspecified</pose>
		<truncated>0</truncated>
		<difficult>0</difficult>
		<polygon>
			<x1>176</x1>
			<y1>268</y1>
			<x2>177</x2>
			<y2>261</y2>
			<x3>185</x3>
			<y3>258</y3>
			<x4>201</x4>
			<y4>260</y4>
			<x5>213</x5>
			<y5>259</y5>
			<x6>230</x6>
			<y6>262</y6>
			<x7>242</x7>
			<y7>264</y7>
			<x8>244</x8>
			<y8>274</y8>
			<x9>245</x9>
			<y9>285</y9>
			<x10>197</x10>
			<y10>286</y10>
			<x11>173</x11>
			<y11>285</y11>
		</polygon>
		<bndbox>
			<xmin>173</xmin>
			<ymin>258</ymin>
			<xmax>245</xmax>
			<ymax>286</ymax>
		</bndbox>
	</object>
	<object>
		<name>nesne</name>
		<occluded>0</occluded>
		<pose>Unspecified</pose>
		<truncated>0</truncated>
		<difficult>0</difficult>
		<polygon>
			<x1>308</x1>
			<y1>275</y1>
			<x2>309</x2>
			<y2>271</y2>
			<x3>313</x3>
			<y3>271</y3>
			<x4>313</x4>
			<y4>275</y4>
			<x5>312</x5>
			<y5>282</y5>
			<x6>311</x6>
			<y6>301</y6>
			<x7>309</x7>
			<y7>309</y7>
			<x8>307</x8>
			<y8>303</y8>
			<x9>307</x9>
			<y9>294</y9>
			<x10>307</x10>
			<y10>287</y10>
			<x11>306</x11>
			<y11>279</y11>
		</polygon>
		<bndbox>
			<xmin>306</xmin>
			<ymin>271</ymin>
			<xmax>313</xmax>
			<ymax>309</ymax>
		</bndbox>
	</object>
	<object>
		<name>nesne</name>
		<occluded>0</occluded>
		<pose>Unspecified</pose>
		<truncated>0</truncated>
		<difficult>0</difficult>
		<polygon>
			<x1>314</x1>
			<y1>277</y1>
			<x2>315</x2>
			<y2>275</y2>
			<x3>316</x3>
			<y3>272</y3>
			<x4>320</x4>
			<y4>274</y4>
			<x5>321</x5>
			<y5>278</y5>
			<x6>323</x6>
			<y6>283</y6>
			<x7>321</x7>
			<y7>289</y7>
			<x8>320</x8>
			<y8>294</y8>
			<x9>320</x9>
			<y9>303</y9>
			<x10>319</x10>
			<y10>308</y10>
			<x11>313</x11>
			<y11>308</y11>
			<x12>312</x12>
			<y12>304</y12>
			<x13>312</x13>
			<y13>297</y13>
			<x14>311</x14>
			<y14>289</y14>
		</polygon>
		<bndbox>
			<xmin>311</xmin>
			<ymin>272</ymin>
			<xmax>323</xmax>
			<ymax>308</ymax>
		</bndbox>
	</object>
	<object>
		<name>nesne</name>
		<occluded>0</occluded>
		<pose>Unspecified</pose>
		<truncated>0</truncated>
		<difficult>0</difficult>
		<polygon>
			<x1>325</x1>
			<y1>283</y1>
			<x2>334</x2>
			<y2>285</y2>
			<x3>342</x3>
			<y3>290</y3>
			<x4>347</x4>
			<y4>303</y4>
			<x5>346</x5>
			<y5>309</y5>
			<x6>320</x6>
			<y6>309</y6>
			<x7>320</x7>
			<y7>306</y7>
			<x8>320</x8>
			<y8>297</y8>
			<x9>320</x9>
			<y9>290</y9>
		</polygon>
		<bndbox>
			<xmin>320</xmin>
			<ymin>283</ymin>
			<xmax>347</xmax>
			<ymax>309</ymax>
		</bndbox>
	</object>
	<object>
		<name>nesne</name>
		<occluded>0</occluded>
		<pose>Unspecified</pose>
		<truncated>0</truncated>
		<difficult>0</difficult>
		<polygon>
			<x1>338</x1>
			<y1>275</y1>
			<x2>337</x2>
			<y2>282</y2>
			<x3>332</x3>
			<y3>282</y3>
			<x4>335</x4>
			<y4>285</y4>
			<x5>355</x5>
			<y5>287</y5>
			<x6>386</x6>
			<y6>287</y6>
			<x7>385</x7>
			<y7>283</y7>
			<x8>371</x8>
			<y8>281</y8>
			<x9>364</x9>
			<y9>277</y9>
			<x10>355</x10>
			<y10>273</y10>
		</polygon>
		<bndbox>
			<xmin>332</xmin>
			<ymin>273</ymin>
			<xmax>386</xmax>
			<ymax>287</ymax>
		</bndbox>
	</object>
	<object>
		<name>nesne</name>
		<occluded>0</occluded>
		<pose>Unspecified</pose>
		<truncated>0</truncated>
		<difficult>0</difficult>
		<polygon>
			<x1>514</x1>
			<y1>302</y1>
			<x2>512</x2>
			<y2>288</y2>
			<x3>511</x3>
			<y3>281</y3>
			<x4>514</x4>
			<y4>274</y4>
			<x5>518</x5>
			<y5>271</y5>
			<x6>519</x6>
			<y6>276</y6>
			<x7>521</x7>
			<y7>282</y7>
			<x8>522</x8>
			<y8>291</y8>
			<x9>521</x9>
			<y9>304</y9>
		</polygon>
		<bndbox>
			<xmin>511</xmin>
			<ymin>271</ymin>
			<xmax>522</xmax>
			<ymax>304</ymax>
		</bndbox>
	</object>
	<object>
		<name>nesne</name>
		<occluded>0</occluded>
		<pose>Unspecified</pose>
		<truncated>0</truncated>
		<difficult>0</difficult>
		<polygon>
			<x1>524</x1>
			<y1>280</y1>
			<x2>525</x2>
			<y2>274</y2>
			<x3>529</x3>
			<y3>274</y3>
			<x4>531</x4>
			<y4>280</y4>
			<x5>533</x5>
			<y5>286</y5>
			<x6>531</x6>
			<y6>294</y6>
			<x7>531</x7>
			<y7>302</y7>
			<x8>529</x8>
			<y8>306</y8>
			<x9>525</x9>
			<y9>302</y9>
			<x10>524</x10>
			<y10>296</y10>
			<x11>525</x11>
			<y11>290</y11>
		</polygon>
		<bndbox>
			<xmin>524</xmin>
			<ymin>274</ymin>
			<xmax>533</xmax>
			<ymax>306</ymax>
		</bndbox>
	</object>
	<object>
		<name>nesne</name>
		<occluded>0</occluded>
		<pose>Unspecified</pose>
		<truncated>0</truncated>
		<difficult>0</difficult>
		<polygon>
			<x1>436</x1>
			<y1>275</y1>
			<x2>440</x2>
			<y2>272</y2>
			<x3>441</x3>
			<y3>278</y3>
			<x4>442</x4>
			<y4>285</y4>
			<x5>442</x5>
			<y5>296</y5>
			<x6>440</x6>
			<y6>302</y6>
			<x7>437</x7>
			<y7>302</y7>
			<x8>436</x8>
			<y8>292</y8>
			<x9>436</x9>
			<y9>286</y9>
			<x10>434</x10>
			<y10>281</y10>
		</polygon>
		<bndbox>
			<xmin>434</xmin>
			<ymin>272</ymin>
			<xmax>442</xmax>
			<ymax>302</ymax>
		</bndbox>
	</object>
	<object>
		<name>nesne</name>
		<occluded>0</occluded>
		<pose>Unspecified</pose>
		<truncated>0</truncated>
		<difficult>0</difficult>
		<polygon>
			<x1>446</x1>
			<y1>273</y1>
			<x2>450</x2>
			<y2>271</y2>
			<x3>451</x3>
			<y3>274</y3>
			<x4>453</x4>
			<y4>278</y4>
			<x5>453</x5>
			<y5>302</y5>
			<x6>448</x6>
			<y6>303</y6>
			<x7>445</x7>
			<y7>300</y7>
			<x8>445</x8>
			<y8>294</y8>
			<x9>444</x9>
			<y9>285</y9>
			<x10>443</x10>
			<y10>281</y10>
			<x11>443</x11>
			<y11>275</y11>
		</polygon>
		<bndbox>
			<xmin>443</xmin>
			<ymin>271</ymin>
			<xmax>453</xmax>
			<ymax>303</ymax>
		</bndbox>
	</object>
	<object>
		<name>nesne</name>
		<occluded>0</occluded>
		<pose>Unspecified</pose>
		<truncated>0</truncated>
		<difficult>0</difficult>
		<polygon>
			<x1>455</x1>
			<y1>275</y1>
			<x2>457</x2>
			<y2>272</y2>
			<x3>458</x3>
			<y3>282</y3>
			<x4>458</x4>
			<y4>302</y4>
			<x5>455</x5>
			<y5>306</y5>
			<x6>453</x6>
			<y6>301</y6>
			<x7>452</x7>
			<y7>290</y7>
			<x8>452</x8>
			<y8>275</y8>
		</polygon>
		<bndbox>
			<xmin>452</xmin>
			<ymin>272</ymin>
			<xmax>458</xmax>
			<ymax>306</ymax>
		</bndbox>
	</object>
	<object>
		<name>nesne</name>
		<occluded>0</occluded>
		<pose>Unspecified</pose>
		<truncated>0</truncated>
		<difficult>0</difficult>
		<polygon>
			<x1>476</x1>
			<y1>301</y1>
			<x2>476</x2>
			<y2>301</y2>
			<x3>476</x3>
			<y3>279</y3>
			<x4>473</x4>
			<y4>272</y4>
			<x5>468</x5>
			<y5>274</y5>
			<x6>469</x6>
			<y6>290</y6>
			<x7>469</x7>
			<y7>304</y7>
		</polygon>
		<bndbox>
			<xmin>468</xmin>
			<ymin>272</ymin>
			<xmax>476</xmax>
			<ymax>304</ymax>
		</bndbox>
	</object>
	<object>
		<name>nesne</name>
		<occluded>0</occluded>
		<pose>Unspecified</pose>
		<truncated>0</truncated>
		<difficult>0</difficult>
		<polygon>
			<x1>489</x1>
			<y1>305</y1>
			<x2>496</x2>
			<y2>305</y2>
			<x3>496</x3>
			<y3>290</y3>
			<x4>496</x4>
			<y4>279</y4>
			<x5>493</x5>
			<y5>272</y5>
			<x6>488</x6>
			<y6>276</y6>
			<x7>488</x7>
			<y7>282</y7>
		</polygon>
		<bndbox>
			<xmin>488</xmin>
			<ymin>272</ymin>
			<xmax>496</xmax>
			<ymax>305</ymax>
		</bndbox>
	</object>
	<object>
		<name>nesne</name>
		<occluded>0</occluded>
		<pose>Unspecified</pose>
		<truncated>0</truncated>
		<difficult>0</difficult>
		<polygon>
			<x1>499</x1>
			<y1>302</y1>
			<x2>507</x2>
			<y2>302</y2>
			<x3>508</x3>
			<y3>284</y3>
			<x4>503</x4>
			<y4>270</y4>
			<x5>500</x5>
			<y5>272</y5>
			<x6>500</x6>
			<y6>282</y6>
			<x7>502</x7>
			<y7>289</y7>
		</polygon>
		<bndbox>
			<xmin>499</xmin>
			<ymin>270</ymin>
			<xmax>508</xmax>
			<ymax>302</ymax>
		</bndbox>
	</object>
	<object>
		<name>nesne</name>
		<occluded>0</occluded>
		<pose>Unspecified</pose>
		<truncated>0</truncated>
		<difficult>0</difficult>
		<polygon>
			<x1>789</x1>
			<y1>240</y1>
			<x2>795</x2>
			<y2>228</y2>
			<x3>805</x3>
			<y3>233</y3>
			<x4>806</x4>
			<y4>250</y4>
			<x5>802</x5>
			<y5>259</y5>
			<x6>791</x6>
			<y6>255</y6>
		</polygon>
		<bndbox>
			<xmin>789</xmin>
			<ymin>228</ymin>
			<xmax>806</xmax>
			<ymax>259</ymax>
		</bndbox>
	</object>
	<object>
		<name>nesne</name>
		<occluded>0</occluded>
		<pose>Unspecified</pose>
		<truncated>0</truncated>
		<difficult>0</difficult>
		<polygon>
			<x1>778</x1>
			<y1>254</y1>
			<x2>784</x2>
			<y2>248</y2>
			<x3>789</x3>
			<y3>246</y3>
			<x4>796</x4>
			<y4>256</y4>
			<x5>798</x5>
			<y5>269</y5>
			<x6>791</x6>
			<y6>276</y6>
			<x7>782</x7>
			<y7>273</y7>
			<x8>778</x8>
			<y8>263</y8>
		</polygon>
		<bndbox>
			<xmin>778</xmin>
			<ymin>246</ymin>
			<xmax>798</xmax>
			<ymax>276</ymax>
		</bndbox>
	</object>
	<object>
		<name>nesne</name>
		<occluded>0</occluded>
		<pose>Unspecified</pose>
		<truncated>0</truncated>
		<difficult>0</difficult>
		<polygon>
			<x1>560</x1>
			<y1>306</y1>
			<x2>559</x2>
			<y2>297</y2>
			<x3>564</x3>
			<y3>298</y3>
			<x4>570</x4>
			<y4>310</y4>
			<x5>569</x5>
			<y5>315</y5>
			<x6>560</x6>
			<y6>315</y6>
		</polygon>
		<bndbox>
			<xmin>559</xmin>
			<ymin>297</ymin>
			<xmax>570</xmax>
			<ymax>315</ymax>
		</bndbox>
	</object>
	<object>
		<name>nesne</name>
		<occluded>0</occluded>
		<pose>Unspecified</pose>
		<truncated>0</truncated>
		<difficult>0</difficult>
		<polygon>
			<x1>692</x1>
			<y1>331</y1>
			<x2>698</x2>
			<y2>320</y2>
			<x3>709</x3>
			<y3>313</y3>
			<x4>709</x4>
			<y4>323</y4>
			<x5>707</x5>
			<y5>340</y5>
			<x6>698</x6>
			<y6>344</y6>
			<x7>692</x7>
			<y7>340</y7>
		</polygon>
		<bndbox>
			<xmin>692</xmin>
			<ymin>313</ymin>
			<xmax>709</xmax>
			<ymax>344</ymax>
		</bndbox>
	</object>
	<object>
		<name>nesne</name>
		<occluded>0</occluded>
		<pose>Unspecified</pose>
		<truncated>0</truncated>
		<difficult>0</difficult>
		<polygon>
			<x1>734</x1>
			<y1>329</y1>
			<x2>734</x2>
			<y2>313</y2>
			<x3>741</x3>
			<y3>314</y3>
			<x4>742</x4>
			<y4>328</y4>
			<x5>747</x5>
			<y5>335</y5>
			<x6>751</x6>
			<y6>344</y6>
			<x7>745</x7>
			<y7>350</y7>
			<x8>736</x8>
			<y8>347</y8>
			<x9>734</x9>
			<y9>340</y9>
		</polygon>
		<bndbox>
			<xmin>734</xmin>
			<ymin>313</ymin>
			<xmax>751</xmax>
			<ymax>350</ymax>
		</bndbox>
	</object>
	<object>
		<name>nesne</name>
		<occluded>0</occluded>
		<pose>Unspecified</pose>
		<truncated>0</truncated>
		<difficult>0</difficult>
		<polygon>
			<x1>756</x1>
			<y1>331</y1>
			<x2>759</x2>
			<y2>315</y2>
			<x3>758</x3>
			<y3>306</y3>
			<x4>766</x4>
			<y4>309</y4>
			<x5>770</x5>
			<y5>323</y5>
			<x6>774</x6>
			<y6>340</y6>
			<x7>766</x7>
			<y7>346</y7>
			<x8>752</x8>
			<y8>348</y8>
			<x9>756</x9>
			<y9>335</y9>
		</polygon>
		<bndbox>
			<xmin>752</xmin>
			<ymin>306</ymin>
			<xmax>774</xmax>
			<ymax>348</ymax>
		</bndbox>
	</object>
	<object>
		<name>nesne</name>
		<occluded>0</occluded>
		<pose>Unspecified</pose>
		<truncated>0</truncated>
		<difficult>0</difficult>
		<polygon>
			<x1>774</x1>
			<y1>318</y1>
			<x2>788</x2>
			<y2>318</y2>
			<x3>788</x3>
			<y3>329</y3>
			<x4>794</x4>
			<y4>340</y4>
			<x5>801</x5>
			<y5>348</y5>
			<x6>805</x6>
			<y6>358</y6>
			<x7>786</x7>
			<y7>357</y7>
			<x8>772</x8>
			<y8>355</y8>
			<x9>769</x9>
			<y9>353</y9>
			<x10>774</x10>
			<y10>343</y10>
			<x11>776</x11>
			<y11>335</y11>
			<x12>772</x12>
			<y12>322</y12>
		</polygon>
		<bndbox>
			<xmin>769</xmin>
			<ymin>318</ymin>
			<xmax>805</xmax>
			<ymax>358</ymax>
		</bndbox>
	</object>
	<object>
		<name>nesne</name>
		<occluded>0</occluded>
		<pose>Unspecified</pose>
		<truncated>0</truncated>
		<difficult>0</difficult>
		<polygon>
			<x1>333</x1>
			<y1>464</y1>
			<x2>363</x2>
			<y2>428</y2>
			<x3>377</x3>
			<y3>410</y3>
			<x4>388</x4>
			<y4>412</y4>
			<x5>348</x5>
			<y5>467</y5>
		</polygon>
		<bndbox>
			<xmin>333</xmin>
			<ymin>410</ymin>
			<xmax>388</xmax>
			<ymax>467</ymax>
		</bndbox>
	</object>
	<object>
		<name>nesne</name>
		<occluded>0</occluded>
		<pose>Unspecified</pose>
		<truncated>0</truncated>
		<difficult>0</difficult>
		<polygon>
			<x1>399</x1>
			<y1>379</y1>
			<x2>417</x2>
			<y2>359</y2>
			<x3>426</x3>
			<y3>358</y3>
			<x4>409</x4>
			<y4>383</y4>
		</polygon>
		<bndbox>
			<xmin>399</xmin>
			<ymin>358</ymin>
			<xmax>426</xmax>
			<ymax>383</ymax>
		</bndbox>
	</object>
	<object>
		<name>nesne</name>
		<occluded>0</occluded>
		<pose>Unspecified</pose>
		<truncated>0</truncated>
		<difficult>0</difficult>
		<polygon>
			<x1>428</x1>
			<y1>347</y1>
			<x2>436</x2>
			<y2>335</y2>
			<x3>442</x3>
			<y3>335</y3>
			<x4>434</x4>
			<y4>349</y4>
		</polygon>
		<bndbox>
			<xmin>428</xmin>
			<ymin>335</ymin>
			<xmax>442</xmax>
			<ymax>349</ymax>
		</bndbox>
	</object>
	<object>
		<name>nesne</name>
		<occluded>0</occluded>
		<pose>Unspecified</pose>
		<truncated>0</truncated>
		<difficult>0</difficult>
		<polygon>
			<x1>442</x1>
			<y1>329</y1>
			<x2>448</x2>
			<y2>322</y2>
			<x3>452</x3>
			<y3>323</y3>
			<x4>446</x4>
			<y4>330</y4>
		</polygon>
		<bndbox>
			<xmin>442</xmin>
			<ymin>322</ymin>
			<xmax>452</xmax>
			<ymax>330</ymax>
		</bndbox>
	</object>
	<object>
		<name>nesne</name>
		<occluded>0</occluded>
		<pose>Unspecified</pose>
		<truncated>0</truncated>
		<difficult>0</difficult>
		<polygon>
			<x1>453</x1>
			<y1>315</y1>
			<x2>453</x2>
			<y2>317</y2>
		</polygon>
		<bndbox>
			<xmin>453</xmin>
			<ymin>315</ymin>
			<xmax>453</xmax>
			<ymax>317</ymax>
		</bndbox>
	</object>
	<object>
		<name>nesne</name>
		<occluded>0</occluded>
		<pose>Unspecified</pose>
		<truncated>0</truncated>
		<difficult>0</difficult>
		<polygon>
			<x1>2</x1>
			<y1>282</y1>
			<x2>22</x2>
			<y2>280</y2>
			<x3>22</x3>
			<y3>296</y3>
			<x4>1</x4>
			<y4>294</y4>
		</polygon>
		<bndbox>
			<xmin>1</xmin>
			<ymin>280</ymin>
			<xmax>22</xmax>
			<ymax>296</ymax>
		</bndbox>
	</object>
	<object>
		<name>nesne</name>
		<occluded>0</occluded>
		<pose>Unspecified</pose>
		<truncated>0</truncated>
		<difficult>0</difficult>
		<polygon>
			<x1>305</x1>
			<y1>285</y1>
			<x2>306</x2>
			<y2>300</y2>
			<x3>64</x3>
			<y3>296</y3>
			<x4>1</x4>
			<y4>296</y4>
			<x5>0</x5>
			<y5>280</y5>
			<x6>198</x6>
			<y6>285</y6>
		</polygon>
		<bndbox>
			<xmin>0</xmin>
			<ymin>280</ymin>
			<xmax>306</xmax>
			<ymax>300</ymax>
		</bndbox>
	</object>
	<object>
		<name>nesne</name>
		<occluded>0</occluded>
		<pose>Unspecified</pose>
		<truncated>0</truncated>
		<difficult>0</difficult>
		<polygon>
			<x1>42</x1>
			<y1>282</y1>
			<x2>43</x2>
			<y2>297</y2>
			<x3>22</x3>
			<y3>296</y3>
			<x4>22</x4>
			<y4>282</y4>
		</polygon>
		<bndbox>
			<xmin>22</xmin>
			<ymin>282</ymin>
			<xmax>43</xmax>
			<ymax>297</ymax>
		</bndbox>
	</object>
	<object>
		<name>nesne</name>
		<occluded>0</occluded>
		<pose>Unspecified</pose>
		<truncated>0</truncated>
		<difficult>0</difficult>
		<polygon>
			<x1>65</x1>
			<y1>282</y1>
			<x2>65</x2>
			<y2>294</y2>
			<x3>41</x3>
			<y3>294</y3>
			<x4>41</x4>
			<y4>280</y4>
		</polygon>
		<bndbox>
			<xmin>41</xmin>
			<ymin>280</ymin>
			<xmax>65</xmax>
			<ymax>294</ymax>
		</bndbox>
	</object>
	<object>
		<name>nesne</name>
		<occluded>0</occluded>
		<pose>Unspecified</pose>
		<truncated>0</truncated>
		<difficult>0</difficult>
		<polygon>
			<x1>64</x1>
			<y1>296</y1>
			<x2>86</x2>
			<y2>296</y2>
			<x3>87</x3>
			<y3>283</y3>
			<x4>65</x4>
			<y4>281</y4>
		</polygon>
		<bndbox>
			<xmin>64</xmin>
			<ymin>281</ymin>
			<xmax>87</xmax>
			<ymax>296</ymax>
		</bndbox>
	</object>
	<object>
		<name>nesne</name>
		<occluded>0</occluded>
		<pose>Unspecified</pose>
		<truncated>0</truncated>
		<difficult>0</difficult>
		<polygon>
			<x1>108</x1>
			<y1>284</y1>
			<x2>108</x2>
			<y2>297</y2>
			<x3>86</x3>
			<y3>297</y3>
			<x4>86</x4>
			<y4>282</y4>
		</polygon>
		<bndbox>
			<xmin>86</xmin>
			<ymin>282</ymin>
			<xmax>108</xmax>
			<ymax>297</ymax>
		</bndbox>
	</object>
	<object>
		<name>nesne</name>
		<occluded>0</occluded>
		<pose>Unspecified</pose>
		<truncated>0</truncated>
		<difficult>0</difficult>
		<polygon>
			<x1>129</x1>
			<y1>296</y1>
			<x2>108</x2>
			<y2>296</y2>
			<x3>109</x3>
			<y3>284</y3>
			<x4>129</x4>
			<y4>283</y4>
		</polygon>
		<bndbox>
			<xmin>108</xmin>
			<ymin>283</ymin>
			<xmax>129</xmax>
			<ymax>296</ymax>
		</bndbox>
	</object>
	<object>
		<name>nesne</name>
		<occluded>0</occluded>
		<pose>Unspecified</pose>
		<truncated>0</truncated>
		<difficult>0</difficult>
		<polygon>
			<x1>150</x1>
			<y1>297</y1>
			<x2>153</x2>
			<y2>284</y2>
			<x3>129</x3>
			<y3>284</y3>
			<x4>129</x4>
			<y4>297</y4>
		</polygon>
		<bndbox>
			<xmin>129</xmin>
			<ymin>284</ymin>
			<xmax>153</xmax>
			<ymax>297</ymax>
		</bndbox>
	</object>
	<object>
		<name>nesne</name>
		<occluded>0</occluded>
		<pose>Unspecified</pose>
		<truncated>0</truncated>
		<difficult>0</difficult>
		<polygon>
			<x1>174</x1>
			<y1>297</y1>
			<x2>174</x2>
			<y2>284</y2>
			<x3>153</x3>
			<y3>283</y3>
			<x4>150</x4>
			<y4>296</y4>
		</polygon>
		<bndbox>
			<xmin>150</xmin>
			<ymin>283</ymin>
			<xmax>174</xmax>
			<ymax>297</ymax>
		</bndbox>
	</object>
	<object>
		<name>nesne</name>
		<occluded>0</occluded>
		<pose>Unspecified</pose>
		<truncated>0</truncated>
		<difficult>0</difficult>
		<polygon>
			<x1>196</x1>
			<y1>299</y1>
			<x2>196</x2>
			<y2>284</y2>
			<x3>175</x3>
			<y3>283</y3>
			<x4>174</x4>
			<y4>296</y4>
		</polygon>
		<bndbox>
			<xmin>174</xmin>
			<ymin>283</ymin>
			<xmax>196</xmax>
			<ymax>299</ymax>
		</bndbox>
	</object>
	<object>
		<name>nesne</name>
		<occluded>0</occluded>
		<pose>Unspecified</pose>
		<truncated>0</truncated>
		<difficult>0</difficult>
		<polygon>
			<x1>218</x1>
			<y1>297</y1>
			<x2>223</x2>
			<y2>285</y2>
			<x3>198</x3>
			<y3>284</y3>
			<x4>196</x4>
			<y4>296</y4>
		</polygon>
		<bndbox>
			<xmin>196</xmin>
			<ymin>284</ymin>
			<xmax>223</xmax>
			<ymax>297</ymax>
		</bndbox>
	</object>
	<object>
		<name>nesne</name>
		<occluded>0</occluded>
		<pose>Unspecified</pose>
		<truncated>0</truncated>
		<difficult>0</difficult>
		<polygon>
			<x1>241</x1>
			<y1>296</y1>
			<x2>245</x2>
			<y2>283</y2>
			<x3>223</x3>
			<y3>284</y3>
			<x4>218</x4>
			<y4>297</y4>
		</polygon>
		<bndbox>
			<xmin>218</xmin>
			<ymin>283</ymin>
			<xmax>245</xmax>
			<ymax>297</ymax>
		</bndbox>
	</object>
	<object>
		<name>nesne</name>
		<occluded>0</occluded>
		<pose>Unspecified</pose>
		<truncated>0</truncated>
		<difficult>0</difficult>
		<polygon>
			<x1>267</x1>
			<y1>296</y1>
			<x2>268</x2>
			<y2>284</y2>
			<x3>245</x3>
			<y3>284</y3>
			<x4>242</x4>
			<y4>296</y4>
		</polygon>
		<bndbox>
			<xmin>242</xmin>
			<ymin>284</ymin>
			<xmax>268</xmax>
			<ymax>296</ymax>
		</bndbox>
	</object>
	<object>
		<name>nesne</name>
		<occluded>0</occluded>
		<pose>Unspecified</pose>
		<truncated>0</truncated>
		<difficult>0</difficult>
		<polygon>
			<x1>289</x1>
			<y1>296</y1>
			<x2>292</x2>
			<y2>284</y2>
			<x3>268</x3>
			<y3>284</y3>
			<x4>266</x4>
			<y4>297</y4>
		</polygon>
		<bndbox>
			<xmin>266</xmin>
			<ymin>284</ymin>
			<xmax>292</xmax>
			<ymax>297</ymax>
		</bndbox>
	</object>
	<object>
		<name>nesne</name>
		<occluded>0</occluded>
		<pose>Unspecified</pose>
		<truncated>0</truncated>
		<difficult>0</difficult>
		<polygon>
			<x1>291</x1>
			<y1>297</y1>
			<x2>291</x2>
			<y2>297</y2>
			<x3>307</x3>
			<y3>298</y3>
			<x4>307</x4>
			<y4>286</y4>
			<x5>291</x5>
			<y5>284</y5>
		</polygon>
		<bndbox>
			<xmin>291</xmin>
			<ymin>284</ymin>
			<xmax>307</xmax>
			<ymax>298</ymax>
		</bndbox>
	</object>
	<object>
		<name>nesne</name>
		<occluded>0</occluded>
		<pose>Unspecified</pose>
		<truncated>0</truncated>
		<difficult>0</difficult>
		<polygon>
			<x1>364</x1>
			<y1>296</y1>
			<x2>363</x2>
			<y2>287</y2>
			<x3>338</x3>
			<y3>285</y3>
			<x4>344</x4>
			<y4>298</y4>
		</polygon>
		<bndbox>
			<xmin>338</xmin>
			<ymin>285</ymin>
			<xmax>364</xmax>
			<ymax>298</ymax>
		</bndbox>
	</object>
	<object>
		<name>nesne</name>
		<occluded>0</occluded>
		<pose>Unspecified</pose>
		<truncated>0</truncated>
		<difficult>0</difficult>
		<polygon>
			<x1>363</x1>
			<y1>299</y1>
			<x2>386</x2>
			<y2>299</y2>
			<x3>384</x3>
			<y3>286</y3>
			<x4>361</x4>
			<y4>286</y4>
		</polygon>
		<bndbox>
			<xmin>361</xmin>
			<ymin>286</ymin>
			<xmax>386</xmax>
			<ymax>299</ymax>
		</bndbox>
	</object>
	<object>
		<name>nesne</name>
		<occluded>0</occluded>
		<pose>Unspecified</pose>
		<truncated>0</truncated>
		<difficult>0</difficult>
		<polygon>
			<x1>411</x1>
			<y1>298</y1>
			<x2>408</x2>
			<y2>288</y2>
			<x3>412</x3>
			<y3>284</y3>
			<x4>386</x4>
			<y4>286</y4>
			<x5>384</x5>
			<y5>291</y5>
			<x6>384</x6>
			<y6>299</y6>
		</polygon>
		<bndbox>
			<xmin>384</xmin>
			<ymin>284</ymin>
			<xmax>412</xmax>
			<ymax>299</ymax>
		</bndbox>
	</object>
	<object>
		<name>nesne</name>
		<occluded>0</occluded>
		<pose>Unspecified</pose>
		<truncated>0</truncated>
		<difficult>0</difficult>
		<polygon>
			<x1>431</x1>
			<y1>298</y1>
			<x2>431</x2>
			<y2>288</y2>
			<x3>433</x3>
			<y3>287</y3>
			<x4>409</x4>
			<y4>285</y4>
			<x5>410</x5>
			<y5>297</y5>
		</polygon>
		<bndbox>
			<xmin>409</xmin>
			<ymin>285</ymin>
			<xmax>433</xmax>
			<ymax>298</ymax>
		</bndbox>
	</object>
	<object>
		<name>nesne</name>
		<occluded>0</occluded>
		<pose>Unspecified</pose>
		<truncated>0</truncated>
		<difficult>0</difficult>
		<polygon>
			<x1>542</x1>
			<y1>289</y1>
			<x2>609</x2>
			<y2>292</y2>
			<x3>669</x3>
			<y3>296</y3>
			<x4>755</x4>
			<y4>305</y4>
			<x5>833</x5>
			<y5>311</y5>
			<x6>832</x6>
			<y6>344</y6>
			<x7>792</x7>
			<y7>339</y7>
			<x8>744</x8>
			<y8>333</y8>
			<x9>703</x9>
			<y9>327</y9>
			<x10>636</x10>
			<y10>315</y10>
			<x11>578</x11>
			<y11>308</y11>
			<x12>539</x12>
			<y12>304</y12>
		</polygon>
		<bndbox>
			<xmin>539</xmin>
			<ymin>289</ymin>
			<xmax>833</xmax>
			<ymax>344</ymax>
		</bndbox>
	</object>
	<object>
		<name>nesne</name>
		<occluded>0</occluded>
		<pose>Unspecified</pose>
		<truncated>0</truncated>
		<difficult>0</difficult>
		<polygon>
			<x1>452</x1>
			<y1>315</y1>
			<x2>458</x2>
			<y2>316</y2>
			<x3>453</x3>
			<y3>321</y3>
			<x4>449</x4>
			<y4>320</y4>
		</polygon>
		<bndbox>
			<xmin>449</xmin>
			<ymin>315</ymin>
			<xmax>458</xmax>
			<ymax>321</ymax>
		</bndbox>
	</object>
	<object>
		<name>nesne</name>
		<occluded>0</occluded>
		<pose>Unspecified</pose>
		<truncated>0</truncated>
		<difficult>0</difficult>
		<polygon>
			<x1>548</x1>
			<y1>289</y1>
			<x2>546</x2>
			<y2>305</y2>
			<x3>564</x3>
			<y3>305</y3>
			<x4>564</x4>
			<y4>289</y4>
		</polygon>
		<bndbox>
			<xmin>546</xmin>
			<ymin>289</ymin>
			<xmax>564</xmax>
			<ymax>305</ymax>
		</bndbox>
	</object>
	<object>
		<name>nesne</name>
		<occluded>0</occluded>
		<pose>Unspecified</pose>
		<truncated>0</truncated>
		<difficult>0</difficult>
		<polygon>
			<x1>579</x1>
			<y1>292</y1>
			<x2>564</x2>
			<y2>290</y2>
			<x3>563</x3>
			<y3>302</y3>
			<x4>568</x4>
			<y4>305</y4>
			<x5>578</x5>
			<y5>306</y5>
		</polygon>
		<bndbox>
			<xmin>563</xmin>
			<ymin>290</ymin>
			<xmax>579</xmax>
			<ymax>306</ymax>
		</bndbox>
	</object>
	<object>
		<name>nesne</name>
		<occluded>0</occluded>
		<pose>Unspecified</pose>
		<truncated>0</truncated>
		<difficult>0</difficult>
		<polygon>
			<x1>601</x1>
			<y1>291</y1>
			<x2>597</x2>
			<y2>309</y2>
			<x3>577</x3>
			<y3>308</y3>
			<x4>580</x4>
			<y4>291</y4>
		</polygon>
		<bndbox>
			<xmin>577</xmin>
			<ymin>291</ymin>
			<xmax>601</xmax>
			<ymax>309</ymax>
		</bndbox>
	</object>
	<object>
		<name>nesne</name>
		<occluded>0</occluded>
		<pose>Unspecified</pose>
		<truncated>0</truncated>
		<difficult>0</difficult>
		<polygon>
			<x1>613</x1>
			<y1>293</y1>
			<x2>612</x2>
			<y2>311</y2>
			<x3>597</x3>
			<y3>308</y3>
			<x4>600</x4>
			<y4>291</y4>
		</polygon>
		<bndbox>
			<xmin>597</xmin>
			<ymin>291</ymin>
			<xmax>613</xmax>
			<ymax>311</ymax>
		</bndbox>
	</object>
	<object>
		<name>nesne</name>
		<occluded>0</occluded>
		<pose>Unspecified</pose>
		<truncated>0</truncated>
		<difficult>0</difficult>
		<polygon>
			<x1>626</x1>
			<y1>293</y1>
			<x2>624</x2>
			<y2>313</y2>
			<x3>611</x3>
			<y3>311</y3>
			<x4>612</x4>
			<y4>292</y4>
		</polygon>
		<bndbox>
			<xmin>611</xmin>
			<ymin>292</ymin>
			<xmax>626</xmax>
			<ymax>313</ymax>
		</bndbox>
	</object>
	<object>
		<name>nesne</name>
		<occluded>0</occluded>
		<pose>Unspecified</pose>
		<truncated>0</truncated>
		<difficult>0</difficult>
		<polygon>
			<x1>640</x1>
			<y1>295</y1>
			<x2>636</x2>
			<y2>315</y2>
			<x3>624</x3>
			<y3>314</y3>
			<x4>626</x4>
			<y4>294</y4>
		</polygon>
		<bndbox>
			<xmin>624</xmin>
			<ymin>294</ymin>
			<xmax>640</xmax>
			<ymax>315</ymax>
		</bndbox>
	</object>
	<object>
		<name>nesne</name>
		<occluded>0</occluded>
		<pose>Unspecified</pose>
		<truncated>0</truncated>
		<difficult>0</difficult>
		<polygon>
			<x1>655</x1>
			<y1>296</y1>
			<x2>650</x2>
			<y2>304</y2>
			<x3>648</x3>
			<y3>319</y3>
			<x4>635</x4>
			<y4>315</y4>
			<x5>640</x5>
			<y5>294</y5>
		</polygon>
		<bndbox>
			<xmin>635</xmin>
			<ymin>294</ymin>
			<xmax>655</xmax>
			<ymax>319</ymax>
		</bndbox>
	</object>
	<object>
		<name>nesne</name>
		<occluded>0</occluded>
		<pose>Unspecified</pose>
		<truncated>0</truncated>
		<difficult>0</difficult>
		<polygon>
			<x1>671</x1>
			<y1>298</y1>
			<x2>664</x2>
			<y2>305</y2>
			<x3>663</x3>
			<y3>321</y3>
			<x4>649</x4>
			<y4>318</y4>
			<x5>650</x5>
			<y5>303</y5>
			<x6>656</x6>
			<y6>296</y6>
		</polygon>
		<bndbox>
			<xmin>649</xmin>
			<ymin>296</ymin>
			<xmax>671</xmax>
			<ymax>321</ymax>
		</bndbox>
	</object>
	<object>
		<name>nesne</name>
		<occluded>0</occluded>
		<pose>Unspecified</pose>
		<truncated>0</truncated>
		<difficult>0</difficult>
		<polygon>
			<x1>694</x1>
			<y1>299</y1>
			<x2>686</x2>
			<y2>306</y2>
			<x3>684</x3>
			<y3>323</y3>
			<x4>664</x4>
			<y4>321</y4>
			<x5>664</x5>
			<y5>307</y5>
			<x6>671</x6>
			<y6>297</y6>
		</polygon>
		<bndbox>
			<xmin>664</xmin>
			<ymin>297</ymin>
			<xmax>694</xmax>
			<ymax>323</ymax>
		</bndbox>
	</object>
	<object>
		<name>nesne</name>
		<occluded>0</occluded>
		<pose>Unspecified</pose>
		<truncated>0</truncated>
		<difficult>0</difficult>
		<polygon>
			<x1>721</x1>
			<y1>301</y1>
			<x2>714</x2>
			<y2>305</y2>
			<x3>712</x3>
			<y3>329</y3>
			<x4>710</x4>
			<y4>328</y4>
			<x5>709</x5>
			<y5>314</y5>
			<x6>706</x6>
			<y6>313</y6>
			<x7>695</x7>
			<y7>322</y7>
			<x8>693</x8>
			<y8>327</y8>
			<x9>685</x9>
			<y9>324</y9>
			<x10>684</x10>
			<y10>309</y10>
			<x11>687</x11>
			<y11>304</y11>
			<x12>694</x12>
			<y12>299</y12>
		</polygon>
		<bndbox>
			<xmin>684</xmin>
			<ymin>299</ymin>
			<xmax>721</xmax>
			<ymax>329</ymax>
		</bndbox>
	</object>
	<object>
		<name>nesne</name>
		<occluded>0</occluded>
		<pose>Unspecified</pose>
		<truncated>0</truncated>
		<difficult>0</difficult>
		<polygon>
			<x1>754</x1>
			<y1>304</y1>
			<x2>745</x2>
			<y2>313</y2>
			<x3>743</x3>
			<y3>315</y3>
			<x4>734</x4>
			<y4>312</y4>
			<x5>733</x5>
			<y5>322</y5>
			<x6>731</x6>
			<y6>332</y6>
			<x7>711</x7>
			<y7>328</y7>
			<x8>714</x8>
			<y8>306</y8>
			<x9>720</x9>
			<y9>301</y9>
		</polygon>
		<bndbox>
			<xmin>711</xmin>
			<ymin>301</ymin>
			<xmax>754</xmax>
			<ymax>332</ymax>
		</bndbox>
	</object>
	<object>
		<name>nesne</name>
		<occluded>0</occluded>
		<pose>Unspecified</pose>
		<truncated>0</truncated>
		<difficult>0</difficult>
		<polygon>
			<x1>755</x1>
			<y1>304</y1>
			<x2>783</x2>
			<y2>307</y2>
			<x3>779</x3>
			<y3>317</y3>
			<x4>770</x4>
			<y4>318</y4>
			<x5>763</x5>
			<y5>308</y5>
			<x6>757</x6>
			<y6>309</y6>
			<x7>756</x7>
			<y7>328</y7>
			<x8>755</x8>
			<y8>337</y8>
			<x9>747</x9>
			<y9>333</y9>
			<x10>742</x10>
			<y10>323</y10>
			<x11>742</x11>
			<y11>315</y11>
			<x12>746</x12>
			<y12>308</y12>
		</polygon>
		<bndbox>
			<xmin>742</xmin>
			<ymin>304</ymin>
			<xmax>783</xmax>
			<ymax>337</ymax>
		</bndbox>
	</object>
	<object>
		<name>nesne</name>
		<occluded>0</occluded>
		<pose>Unspecified</pose>
		<truncated>0</truncated>
		<difficult>0</difficult>
		<polygon>
			<x1>784</x1>
			<y1>306</y1>
			<x2>783</x2>
			<y2>318</y2>
			<x3>788</x3>
			<y3>319</y3>
			<x4>789</x4>
			<y4>326</y4>
			<x5>793</x5>
			<y5>340</y5>
			<x6>832</x6>
			<y6>345</y6>
			<x7>833</x7>
			<y7>333</y7>
			<x8>833</x8>
			<y8>317</y8>
			<x9>837</x9>
			<y9>315</y9>
			<x10>836</x10>
			<y10>311</y10>
			<x11>808</x11>
			<y11>309</y11>
		</polygon>
		<bndbox>
			<xmin>783</xmin>
			<ymin>306</ymin>
			<xmax>837</xmax>
			<ymax>345</ymax>
		</bndbox>
	</object>
	<object>
		<name>nesne</name>
		<occluded>0</occluded>
		<pose>Unspecified</pose>
		<truncated>0</truncated>
		<difficult>0</difficult>
		<polygon>
			<x1>288</x1>
			<y1>523</y1>
			<x2>351</x2>
			<y2>442</y2>
			<x3>391</x3>
			<y3>385</y3>
			<x4>416</x4>
			<y4>357</y4>
			<x5>435</x5>
			<y5>333</y5>
			<x6>454</x6>
			<y6>311</y6>
			<x7>528</x7>
			<y7>307</y7>
			<x8>562</x8>
			<y8>337</y8>
			<x9>623</x9>
			<y9>393</y9>
			<x10>709</x10>
			<y10>470</y10>
			<x11>771</x11>
			<y11>525</y11>
			<x12>743</x12>
			<y12>524</y12>
		</polygon>
		<bndbox>
			<xmin>288</xmin>
			<ymin>307</ymin>
			<xmax>771</xmax>
			<ymax>525</ymax>
		</bndbox>
	</object>
	<object>
		<name>nesne</name>
		<occluded>0</occluded>
		<pose>Unspecified</pose>
		<truncated>0</truncated>
		<difficult>0</difficult>
		<polygon>
			<x1>519</x1>
			<y1>306</y1>
			<x2>526</x2>
			<y2>306</y2>
			<x3>563</x3>
			<y3>338</y3>
			<x4>694</x4>
			<y4>457</y4>
			<x5>769</x5>
			<y5>523</y5>
			<x6>762</x6>
			<y6>513</y6>
			<x7>742</x7>
			<y7>527</y7>
			<x8>724</x8>
			<y8>503</y8>
			<x9>712</x9>
			<y9>492</y9>
			<x10>707</x10>
			<y10>485</y10>
			<x11>677</x11>
			<y11>455</y11>
			<x12>578</x12>
			<y12>360</y12>
			<x13>546</x13>
			<y13>330</y13>
			<x14>524</x14>
			<y14>310</y14>
		</polygon>
		<bndbox>
			<xmin>519</xmin>
			<ymin>306</ymin>
			<xmax>769</xmax>
			<ymax>527</ymax>
		</bndbox>
	</object>
	<object>
		<name>nesne</name>
		<occluded>0</occluded>
		<pose>Unspecified</pose>
		<truncated>0</truncated>
		<difficult>0</difficult>
		<polygon>
			<x1>0</x1>
			<y1>453</y1>
			<x2>88</x2>
			<y2>421</y2>
			<x3>175</x3>
			<y3>388</y3>
			<x4>236</x4>
			<y4>363</y4>
			<x5>279</x5>
			<y5>347</y5>
			<x6>283</x6>
			<y6>345</y6>
			<x7>259</x7>
			<y7>339</y7>
			<x8>172</x8>
			<y8>339</y8>
			<x9>48</x9>
			<y9>335</y9>
			<x10>0</x10>
			<y10>339</y10>
			<x11>0</x11>
			<y11>332</y11>
			<x12>48</x12>
			<y12>332</y12>
			<x13>132</x13>
			<y13>332</y13>
			<x14>196</x14>
			<y14>334</y14>
			<x15>256</x15>
			<y15>335</y15>
			<x16>285</x16>
			<y16>339</y16>
			<x17>294</x17>
			<y17>346</y17>
			<x18>271</x18>
			<y18>356</y18>
			<x19>219</x19>
			<y19>374</y19>
			<x20>125</x20>
			<y20>414</y20>
			<x21>45</x21>
			<y21>443</y21>
			<x22>0</x22>
			<y22>461</y22>
		</polygon>
		<bndbox>
			<xmin>0</xmin>
			<ymin>332</ymin>
			<xmax>294</xmax>
			<ymax>461</ymax>
		</bndbox>
	</object>
	<object>
		<name>nesne</name>
		<occluded>0</occluded>
		<pose>Unspecified</pose>
		<truncated>0</truncated>
		<difficult>0</difficult>
		<polygon>
			<x1>0</x1>
			<y1>451</y1>
			<x2>207</x2>
			<y2>372</y2>
			<x3>282</x3>
			<y3>346</y3>
			<x4>372</x4>
			<y4>315</y4>
			<x5>394</x5>
			<y5>307</y5>
			<x6>403</x6>
			<y6>302</y6>
			<x7>465</x7>
			<y7>305</y7>
			<x8>445</x8>
			<y8>336</y8>
			<x9>397</x9>
			<y9>400</y9>
			<x10>337</x10>
			<y10>486</y10>
			<x11>307</x11>
			<y11>524</y11>
			<x12>0</x12>
			<y12>525</y12>
		</polygon>
		<bndbox>
			<xmin>0</xmin>
			<ymin>302</ymin>
			<xmax>465</xmax>
			<ymax>525</ymax>
		</bndbox>
	</object>
	<object>
		<name>nesne</name>
		<occluded>0</occluded>
		<pose>Unspecified</pose>
		<truncated>0</truncated>
		<difficult>0</difficult>
		<polygon>
			<x1>0</x1>
			<y1>326</y1>
			<x2>1</x2>
			<y2>311</y2>
			<x3>22</x3>
			<y3>312</y3>
			<x4>53</x4>
			<y4>311</y4>
			<x5>105</x5>
			<y5>305</y5>
			<x6>126</x6>
			<y6>304</y6>
			<x7>122</x7>
			<y7>298</y7>
			<x8>189</x8>
			<y8>299</y8>
			<x9>244</x9>
			<y9>299</y9>
			<x10>235</x10>
			<y10>304</y10>
			<x11>202</x11>
			<y11>307</y11>
			<x12>161</x12>
			<y12>314</y12>
			<x13>187</x13>
			<y13>314</y13>
			<x14>259</x14>
			<y14>316</y14>
			<x15>333</x15>
			<y15>318</y15>
			<x16>357</x16>
			<y16>316</y16>
			<x17>381</x17>
			<y17>308</y17>
			<x18>397</x18>
			<y18>301</y18>
			<x19>400</x19>
			<y19>299</y19>
			<x20>426</x20>
			<y20>299</y20>
			<x21>437</x21>
			<y21>300</y21>
			<x22>450</x22>
			<y22>302</y22>
			<x23>466</x23>
			<y23>301</y23>
			<x24>471</x24>
			<y24>307</y24>
			<x25>492</x25>
			<y25>304</y25>
			<x26>523</x26>
			<y26>304</y26>
			<x27>528</x27>
			<y27>305</y27>
			<x28>545</x28>
			<y28>319</y28>
			<x29>576</x29>
			<y29>320</y29>
			<x30>622</x30>
			<y30>324</y30>
			<x31>645</x31>
			<y31>326</y31>
			<x32>665</x32>
			<y32>334</y32>
			<x33>712</x33>
			<y33>348</y33>
			<x34>784</x34>
			<y34>376</y34>
			<x35>772</x35>
			<y35>386</y35>
			<x36>719</x36>
			<y36>407</y36>
			<x37>666</x37>
			<y37>427</y37>
			<x38>724</x38>
			<y38>479</y38>
			<x39>774</x39>
			<y39>524</y39>
			<x40>0</x40>
			<y40>525</y40>
			<x41>0</x41>
			<y41>449</y41>
			<x42>64</x42>
			<y42>426</y42>
			<x43>155</x43>
			<y43>392</y43>
			<x44>246</x44>
			<y44>357</y44>
			<x45>279</x45>
			<y45>346</y45>
			<x46>268</x46>
			<y46>341</y46>
			<x47>224</x47>
			<y47>340</y47>
			<x48>150</x48>
			<y48>340</y48>
			<x49>84</x49>
			<y49>338</y49>
			<x50>33</x50>
			<y50>338</y50>
			<x51>0</x51>
			<y51>339</y51>
		</polygon>
		<bndbox>
			<xmin>0</xmin>
			<ymin>298</ymin>
			<xmax>784</xmax>
			<ymax>525</ymax>
		</bndbox>
	</object>
	<object>
		<name>nesne</name>
		<occluded>0</occluded>
		<pose>Unspecified</pose>
		<truncated>0</truncated>
		<difficult>0</difficult>
		<polygon>
			<x1>544</x1>
			<y1>320</y1>
			<x2>583</x2>
			<y2>323</y2>
			<x3>632</x3>
			<y3>328</y3>
			<x4>648</x4>
			<y4>328</y4>
			<x5>672</x5>
			<y5>339</y5>
			<x6>716</x6>
			<y6>353</y6>
			<x7>774</x7>
			<y7>374</y7>
			<x8>783</x8>
			<y8>379</y8>
			<x9>758</x9>
			<y9>392</y9>
			<x10>699</x10>
			<y10>413</y10>
			<x11>662</x11>
			<y11>428</y11>
			<x12>653</x12>
			<y12>422</y12>
			<x13>683</x13>
			<y13>409</y13>
			<x14>736</x14>
			<y14>390</y14>
			<x15>765</x15>
			<y15>379</y15>
			<x16>756</x16>
			<y16>373</y16>
			<x17>712</x17>
			<y17>358</y17>
			<x18>680</x18>
			<y18>346</y18>
			<x19>650</x19>
			<y19>332</y19>
			<x20>632</x20>
			<y20>331</y20>
			<x21>608</x21>
			<y21>328</y21>
			<x22>573</x22>
			<y22>325</y22>
			<x23>547</x23>
			<y23>325</y23>
		</polygon>
		<bndbox>
			<xmin>544</xmin>
			<ymin>320</ymin>
			<xmax>783</xmax>
			<ymax>428</ymax>
		</bndbox>
	</object>
</annotation>
