<annotation>
	<folder>C:\Users\Asus\Desktop\nesne_hüseyin</folder>
	<filename>1680948280818.jpg</filename>
	<path>C:\Users\Asus\Desktop\nesne_hüseyin\1680948280818.jpg</path>
	<source>
		<database>Unknown</database>
		<annotation>Unknown</annotation>
		<image>Unknown</image>
	</source>
	<size>
		<width>930</width>
		<height>530</height>
		<depth>3</depth>
	</size>
	<segmented>0</segmented>
	<object>
		<name>nesne</name>
		<occluded>0</occluded>
		<pose>Unspecified</pose>
		<truncated>0</truncated>
		<difficult>0</difficult>
		<polygon>
			<x1>106</x1>
			<y1>212</y1>
			<x2>120</x2>
			<y2>213</y2>
			<x3>120</x3>
			<y3>240</y3>
			<x4>108</x4>
			<y4>241</y4>
		</polygon>
		<bndbox>
			<xmin>106</xmin>
			<ymin>212</ymin>
			<xmax>120</xmax>
			<ymax>241</ymax>
		</bndbox>
	</object>
	<object>
		<name>nesne</name>
		<occluded>0</occluded>
		<pose>Unspecified</pose>
		<truncated>0</truncated>
		<difficult>0</difficult>
		<polygon>
			<x1>71</x1>
			<y1>232</y1>
			<x2>81</x2>
			<y2>231</y2>
			<x3>93</x3>
			<y3>236</y3>
			<x4>102</x4>
			<y4>244</y4>
			<x5>107</x5>
			<y5>258</y5>
			<x6>104</x6>
			<y6>268</y6>
			<x7>100</x7>
			<y7>276</y7>
			<x8>89</x8>
			<y8>282</y8>
			<x9>74</x9>
			<y9>285</y9>
			<x10>62</x10>
			<y10>278</y10>
			<x11>54</x11>
			<y11>270</y11>
			<x12>52</x12>
			<y12>262</y12>
			<x13>52</x13>
			<y13>249</y13>
			<x14>61</x14>
			<y14>240</y14>
			<x15>69</x15>
			<y15>236</y15>
		</polygon>
		<bndbox>
			<xmin>52</xmin>
			<ymin>231</ymin>
			<xmax>107</xmax>
			<ymax>285</ymax>
		</bndbox>
	</object>
	<object>
		<name>nesne</name>
		<occluded>0</occluded>
		<pose>Unspecified</pose>
		<truncated>0</truncated>
		<difficult>0</difficult>
		<polygon>
			<x1>30</x1>
			<y1>350</y1>
			<x2>26</x2>
			<y2>332</y2>
			<x3>24</x3>
			<y3>314</y3>
			<x4>22</x4>
			<y4>309</y4>
			<x5>16</x5>
			<y5>298</y5>
			<x6>17</x6>
			<y6>291</y6>
			<x7>24</x7>
			<y7>286</y7>
			<x8>28</x8>
			<y8>275</y8>
			<x9>38</x9>
			<y9>274</y9>
			<x10>38</x10>
			<y10>283</y10>
			<x11>41</x11>
			<y11>287</y11>
			<x12>47</x12>
			<y12>288</y12>
			<x13>48</x13>
			<y13>296</y13>
			<x14>47</x14>
			<y14>304</y14>
			<x15>44</x15>
			<y15>311</y15>
			<x16>44</x16>
			<y16>313</y16>
			<x17>46</x17>
			<y17>324</y17>
			<x18>47</x18>
			<y18>328</y18>
			<x19>46</x19>
			<y19>336</y19>
			<x20>46</x20>
			<y20>348</y20>
			<x21>41</x21>
			<y21>353</y21>
			<x22>40</x22>
			<y22>350</y22>
			<x23>37</x23>
			<y23>328</y23>
			<x24>35</x24>
			<y24>326</y24>
			<x25>33</x25>
			<y25>341</y25>
			<x26>34</x26>
			<y26>352</y26>
			<x27>29</x27>
			<y27>346</y27>
		</polygon>
		<bndbox>
			<xmin>16</xmin>
			<ymin>274</ymin>
			<xmax>48</xmax>
			<ymax>353</ymax>
		</bndbox>
	</object>
	<object>
		<name>nesne</name>
		<occluded>0</occluded>
		<pose>Unspecified</pose>
		<truncated>0</truncated>
		<difficult>0</difficult>
		<polygon>
			<x1>50</x1>
			<y1>348</y1>
			<x2>56</x2>
			<y2>330</y2>
			<x3>58</x3>
			<y3>319</y3>
			<x4>56</x4>
			<y4>302</y4>
			<x5>58</x5>
			<y5>294</y5>
			<x6>62</x6>
			<y6>287</y6>
			<x7>62</x7>
			<y7>277</y7>
			<x8>70</x8>
			<y8>282</y8>
			<x9>75</x9>
			<y9>290</y9>
			<x10>76</x10>
			<y10>305</y10>
			<x11>76</x11>
			<y11>320</y11>
			<x12>75</x12>
			<y12>336</y12>
			<x13>76</x13>
			<y13>355</y13>
			<x14>68</x14>
			<y14>349</y14>
			<x15>69</x15>
			<y15>328</y15>
			<x16>66</x16>
			<y16>331</y16>
			<x17>62</x17>
			<y17>350</y17>
		</polygon>
		<bndbox>
			<xmin>50</xmin>
			<ymin>277</ymin>
			<xmax>76</xmax>
			<ymax>355</ymax>
		</bndbox>
	</object>
	<object>
		<name>nesne</name>
		<occluded>0</occluded>
		<pose>Unspecified</pose>
		<truncated>0</truncated>
		<difficult>0</difficult>
		<polygon>
			<x1>94</x1>
			<y1>348</y1>
			<x2>94</x2>
			<y2>330</y2>
			<x3>96</x3>
			<y3>316</y3>
			<x4>96</x4>
			<y4>298</y4>
			<x5>93</x5>
			<y5>292</y5>
			<x6>91</x6>
			<y6>283</y6>
			<x7>82</x7>
			<y7>283</y7>
			<x8>82</x8>
			<y8>292</y8>
			<x9>85</x9>
			<y9>302</y9>
			<x10>83</x10>
			<y10>316</y10>
			<x11>82</x11>
			<y11>350</y11>
		</polygon>
		<bndbox>
			<xmin>82</xmin>
			<ymin>283</ymin>
			<xmax>96</xmax>
			<ymax>350</ymax>
		</bndbox>
	</object>
	<object>
		<name>nesne</name>
		<occluded>0</occluded>
		<pose>Unspecified</pose>
		<truncated>0</truncated>
		<difficult>0</difficult>
		<polygon>
			<x1>124</x1>
			<y1>291</y1>
			<x2>129</x2>
			<y2>282</y2>
			<x3>138</x3>
			<y3>272</y3>
			<x4>148</x4>
			<y4>278</y4>
			<x5>154</x5>
			<y5>295</y5>
			<x6>154</x6>
			<y6>298</y6>
			<x7>154</x7>
			<y7>304</y7>
			<x8>158</x8>
			<y8>322</y8>
			<x9>160</x9>
			<y9>334</y9>
			<x10>148</x10>
			<y10>341</y10>
			<x11>144</x11>
			<y11>331</y11>
			<x12>146</x12>
			<y12>308</y12>
			<x13>142</x13>
			<y13>299</y13>
			<x14>134</x14>
			<y14>294</y14>
		</polygon>
		<bndbox>
			<xmin>124</xmin>
			<ymin>272</ymin>
			<xmax>160</xmax>
			<ymax>341</ymax>
		</bndbox>
	</object>
	<object>
		<name>nesne</name>
		<occluded>0</occluded>
		<pose>Unspecified</pose>
		<truncated>0</truncated>
		<difficult>0</difficult>
		<polygon>
			<x1>105</x1>
			<y1>304</y1>
			<x2>142</x2>
			<y2>302</y2>
			<x3>144</x3>
			<y3>314</y3>
			<x4>143</x4>
			<y4>339</y4>
			<x5>131</x5>
			<y5>344</y5>
			<x6>128</x6>
			<y6>336</y6>
			<x7>96</x7>
			<y7>337</y7>
			<x8>95</x8>
			<y8>331</y8>
			<x9>96</x9>
			<y9>303</y9>
		</polygon>
		<bndbox>
			<xmin>95</xmin>
			<ymin>302</ymin>
			<xmax>144</xmax>
			<ymax>344</ymax>
		</bndbox>
	</object>
	<object>
		<name>nesne</name>
		<occluded>0</occluded>
		<pose>Unspecified</pose>
		<truncated>0</truncated>
		<difficult>0</difficult>
		<polygon>
			<x1>170</x1>
			<y1>306</y1>
			<x2>168</x2>
			<y2>331</y2>
			<x3>162</x3>
			<y3>333</y3>
			<x4>154</x4>
			<y4>304</y4>
		</polygon>
		<bndbox>
			<xmin>154</xmin>
			<ymin>304</ymin>
			<xmax>170</xmax>
			<ymax>333</ymax>
		</bndbox>
	</object>
	<object>
		<name>nesne</name>
		<occluded>0</occluded>
		<pose>Unspecified</pose>
		<truncated>0</truncated>
		<difficult>0</difficult>
		<polygon>
			<x1>174</x1>
			<y1>306</y1>
			<x2>214</x2>
			<y2>307</y2>
			<x3>211</x3>
			<y3>334</y3>
			<x4>168</x4>
			<y4>334</y4>
		</polygon>
		<bndbox>
			<xmin>168</xmin>
			<ymin>306</ymin>
			<xmax>214</xmax>
			<ymax>334</ymax>
		</bndbox>
	</object>
	<object>
		<name>nesne</name>
		<occluded>0</occluded>
		<pose>Unspecified</pose>
		<truncated>0</truncated>
		<difficult>0</difficult>
		<polygon>
			<x1>260</x1>
			<y1>310</y1>
			<x2>258</x2>
			<y2>336</y2>
			<x3>213</x3>
			<y3>335</y3>
			<x4>214</x4>
			<y4>307</y4>
			<x5>260</x5>
			<y5>306</y5>
			<x6>255</x6>
			<y6>309</y6>
		</polygon>
		<bndbox>
			<xmin>213</xmin>
			<ymin>306</ymin>
			<xmax>260</xmax>
			<ymax>336</ymax>
		</bndbox>
	</object>
	<object>
		<name>nesne</name>
		<occluded>0</occluded>
		<pose>Unspecified</pose>
		<truncated>0</truncated>
		<difficult>0</difficult>
		<polygon>
			<x1>305</x1>
			<y1>308</y1>
			<x2>300</x2>
			<y2>339</y2>
			<x3>258</x3>
			<y3>336</y3>
			<x4>261</x4>
			<y4>308</y4>
		</polygon>
		<bndbox>
			<xmin>258</xmin>
			<ymin>308</ymin>
			<xmax>305</xmax>
			<ymax>339</ymax>
		</bndbox>
	</object>
	<object>
		<name>nesne</name>
		<occluded>0</occluded>
		<pose>Unspecified</pose>
		<truncated>0</truncated>
		<difficult>0</difficult>
		<polygon>
			<x1>353</x1>
			<y1>310</y1>
			<x2>352</x2>
			<y2>339</y2>
			<x3>302</x3>
			<y3>337</y3>
			<x4>303</x4>
			<y4>308</y4>
		</polygon>
		<bndbox>
			<xmin>302</xmin>
			<ymin>308</ymin>
			<xmax>353</xmax>
			<ymax>339</ymax>
		</bndbox>
	</object>
	<object>
		<name>nesne</name>
		<occluded>0</occluded>
		<pose>Unspecified</pose>
		<truncated>0</truncated>
		<difficult>0</difficult>
		<polygon>
			<x1>405</x1>
			<y1>312</y1>
			<x2>405</x2>
			<y2>342</y2>
			<x3>354</x3>
			<y3>339</y3>
			<x4>355</x4>
			<y4>309</y4>
		</polygon>
		<bndbox>
			<xmin>354</xmin>
			<ymin>309</ymin>
			<xmax>405</xmax>
			<ymax>342</ymax>
		</bndbox>
	</object>
	<object>
		<name>nesne</name>
		<occluded>0</occluded>
		<pose>Unspecified</pose>
		<truncated>0</truncated>
		<difficult>0</difficult>
		<polygon>
			<x1>463</x1>
			<y1>311</y1>
			<x2>462</x2>
			<y2>345</y2>
			<x3>405</x3>
			<y3>342</y3>
			<x4>405</x4>
			<y4>310</y4>
		</polygon>
		<bndbox>
			<xmin>405</xmin>
			<ymin>310</ymin>
			<xmax>463</xmax>
			<ymax>345</ymax>
		</bndbox>
	</object>
	<object>
		<name>nesne</name>
		<occluded>0</occluded>
		<pose>Unspecified</pose>
		<truncated>0</truncated>
		<difficult>0</difficult>
		<polygon>
			<x1>520</x1>
			<y1>313</y1>
			<x2>521</x2>
			<y2>346</y2>
			<x3>462</x3>
			<y3>346</y3>
			<x4>463</x4>
			<y4>310</y4>
		</polygon>
		<bndbox>
			<xmin>462</xmin>
			<ymin>310</ymin>
			<xmax>521</xmax>
			<ymax>346</ymax>
		</bndbox>
	</object>
	<object>
		<name>nesne</name>
		<occluded>0</occluded>
		<pose>Unspecified</pose>
		<truncated>0</truncated>
		<difficult>0</difficult>
		<polygon>
			<x1>584</x1>
			<y1>313</y1>
			<x2>586</x2>
			<y2>350</y2>
			<x3>521</x3>
			<y3>345</y3>
			<x4>520</x4>
			<y4>312</y4>
		</polygon>
		<bndbox>
			<xmin>520</xmin>
			<ymin>312</ymin>
			<xmax>586</xmax>
			<ymax>350</ymax>
		</bndbox>
	</object>
	<object>
		<name>nesne</name>
		<occluded>0</occluded>
		<pose>Unspecified</pose>
		<truncated>0</truncated>
		<difficult>0</difficult>
		<polygon>
			<x1>651</x1>
			<y1>315</y1>
			<x2>651</x2>
			<y2>350</y2>
			<x3>584</x3>
			<y3>348</y3>
			<x4>583</x4>
			<y4>314</y4>
		</polygon>
		<bndbox>
			<xmin>583</xmin>
			<ymin>314</ymin>
			<xmax>651</xmax>
			<ymax>350</ymax>
		</bndbox>
	</object>
	<object>
		<name>nesne</name>
		<occluded>0</occluded>
		<pose>Unspecified</pose>
		<truncated>0</truncated>
		<difficult>0</difficult>
		<polygon>
			<x1>724</x1>
			<y1>314</y1>
			<x2>725</x2>
			<y2>350</y2>
			<x3>650</x3>
			<y3>350</y3>
			<x4>651</x4>
			<y4>316</y4>
		</polygon>
		<bndbox>
			<xmin>650</xmin>
			<ymin>314</ymin>
			<xmax>725</xmax>
			<ymax>350</ymax>
		</bndbox>
	</object>
	<object>
		<name>nesne</name>
		<occluded>0</occluded>
		<pose>Unspecified</pose>
		<truncated>0</truncated>
		<difficult>0</difficult>
		<polygon>
			<x1>791</x1>
			<y1>316</y1>
			<x2>791</x2>
			<y2>355</y2>
			<x3>724</x3>
			<y3>352</y3>
			<x4>726</x4>
			<y4>314</y4>
		</polygon>
		<bndbox>
			<xmin>724</xmin>
			<ymin>314</ymin>
			<xmax>791</xmax>
			<ymax>355</ymax>
		</bndbox>
	</object>
	<object>
		<name>nesne</name>
		<occluded>0</occluded>
		<pose>Unspecified</pose>
		<truncated>0</truncated>
		<difficult>0</difficult>
		<polygon>
			<x1>790</x1>
			<y1>355</y1>
			<x2>653</x2>
			<y2>349</y2>
			<x3>431</x3>
			<y3>344</y3>
			<x4>162</x4>
			<y4>333</y4>
			<x5>154</x5>
			<y5>304</y5>
			<x6>465</x6>
			<y6>309</y6>
			<x7>788</x7>
			<y7>314</y7>
		</polygon>
		<bndbox>
			<xmin>154</xmin>
			<ymin>304</ymin>
			<xmax>790</xmax>
			<ymax>355</ymax>
		</bndbox>
	</object>
	<object>
		<name>nesne</name>
		<occluded>0</occluded>
		<pose>Unspecified</pose>
		<truncated>0</truncated>
		<difficult>0</difficult>
		<polygon>
			<x1>111</x1>
			<y1>275</y1>
			<x2>111</x2>
			<y2>260</y2>
			<x3>151</x3>
			<y3>261</y3>
			<x4>166</x4>
			<y4>264</y4>
			<x5>170</x5>
			<y5>274</y5>
			<x6>175</x6>
			<y6>276</y6>
			<x7>180</x7>
			<y7>281</y7>
			<x8>188</x8>
			<y8>288</y8>
			<x9>184</x9>
			<y9>294</y9>
			<x10>185</x10>
			<y10>299</y10>
			<x11>178</x11>
			<y11>303</y11>
			<x12>178</x12>
			<y12>295</y12>
			<x13>167</x13>
			<y13>294</y13>
			<x14>154</x14>
			<y14>292</y14>
			<x15>150</x15>
			<y15>279</y15>
			<x16>139</x16>
			<y16>273</y16>
			<x17>131</x17>
			<y17>280</y17>
			<x18>124</x18>
			<y18>289</y18>
			<x19>122</x19>
			<y19>290</y19>
			<x20>113</x20>
			<y20>290</y20>
			<x21>109</x21>
			<y21>287</y21>
		</polygon>
		<bndbox>
			<xmin>109</xmin>
			<ymin>260</ymin>
			<xmax>188</xmax>
			<ymax>303</ymax>
		</bndbox>
	</object>
	<object>
		<name>nesne</name>
		<occluded>0</occluded>
		<pose>Unspecified</pose>
		<truncated>0</truncated>
		<difficult>0</difficult>
		<polygon>
			<x1>192</x1>
			<y1>287</y1>
			<x2>243</x2>
			<y2>287</y2>
			<x3>262</x3>
			<y3>287</y3>
			<x4>265</x4>
			<y4>280</y4>
			<x5>263</x5>
			<y5>271</y5>
			<x6>284</x6>
			<y6>273</y6>
			<x7>289</x7>
			<y7>282</y7>
			<x8>279</x8>
			<y8>288</y8>
			<x9>272</x9>
			<y9>295</y9>
			<x10>273</x10>
			<y10>298</y10>
			<x11>238</x11>
			<y11>299</y11>
			<x12>233</x12>
			<y12>304</y12>
			<x13>224</x13>
			<y13>300</y13>
			<x14>218</x14>
			<y14>304</y14>
			<x15>213</x15>
			<y15>304</y15>
			<x16>204</x16>
			<y16>302</y16>
			<x17>200</x17>
			<y17>293</y17>
		</polygon>
		<bndbox>
			<xmin>192</xmin>
			<ymin>271</ymin>
			<xmax>289</xmax>
			<ymax>304</ymax>
		</bndbox>
	</object>
	<object>
		<name>nesne</name>
		<occluded>0</occluded>
		<pose>Unspecified</pose>
		<truncated>0</truncated>
		<difficult>0</difficult>
		<polygon>
			<x1>290</x1>
			<y1>284</y1>
			<x2>306</x2>
			<y2>284</y2>
			<x3>311</x3>
			<y3>286</y3>
			<x4>308</x4>
			<y4>292</y4>
			<x5>306</x5>
			<y5>303</y5>
			<x6>289</x6>
			<y6>303</y6>
			<x7>280</x7>
			<y7>296</y7>
			<x8>277</x8>
			<y8>292</y8>
			<x9>290</x9>
			<y9>281</y9>
		</polygon>
		<bndbox>
			<xmin>277</xmin>
			<ymin>281</ymin>
			<xmax>311</xmax>
			<ymax>303</ymax>
		</bndbox>
	</object>
	<object>
		<name>nesne</name>
		<occluded>0</occluded>
		<pose>Unspecified</pose>
		<truncated>0</truncated>
		<difficult>0</difficult>
		<polygon>
			<x1>312</x1>
			<y1>285</y1>
			<x2>338</x2>
			<y2>283</y2>
			<x3>357</x3>
			<y3>293</y3>
			<x4>360</x4>
			<y4>300</y4>
			<x5>354</x5>
			<y5>303</y5>
			<x6>348</x6>
			<y6>301</y6>
			<x7>329</x7>
			<y7>301</y7>
			<x8>328</x8>
			<y8>303</y8>
			<x9>320</x9>
			<y9>303</y9>
			<x10>319</x10>
			<y10>300</y10>
			<x11>307</x11>
			<y11>302</y11>
			<x12>309</x12>
			<y12>289</y12>
		</polygon>
		<bndbox>
			<xmin>307</xmin>
			<ymin>283</ymin>
			<xmax>360</xmax>
			<ymax>303</ymax>
		</bndbox>
	</object>
	<object>
		<name>nesne</name>
		<occluded>0</occluded>
		<pose>Unspecified</pose>
		<truncated>0</truncated>
		<difficult>0</difficult>
		<polygon>
			<x1>377</x1>
			<y1>257</y1>
			<x2>410</x2>
			<y2>258</y2>
			<x3>413</x3>
			<y3>261</y3>
			<x4>456</x4>
			<y4>263</y4>
			<x5>459</x5>
			<y5>278</y5>
			<x6>463</x6>
			<y6>291</y6>
			<x7>458</x7>
			<y7>300</y7>
			<x8>453</x8>
			<y8>302</y8>
			<x9>449</x9>
			<y9>301</y9>
			<x10>444</x10>
			<y10>305</y10>
			<x11>442</x11>
			<y11>302</y11>
			<x12>416</x12>
			<y12>300</y12>
			<x13>412</x13>
			<y13>305</y13>
			<x14>405</x14>
			<y14>301</y14>
			<x15>383</x15>
			<y15>300</y15>
			<x16>367</x16>
			<y16>300</y16>
			<x17>367</x17>
			<y17>281</y17>
			<x18>366</x18>
			<y18>268</y18>
			<x19>370</x19>
			<y19>263</y19>
		</polygon>
		<bndbox>
			<xmin>366</xmin>
			<ymin>257</ymin>
			<xmax>463</xmax>
			<ymax>305</ymax>
		</bndbox>
	</object>
	<object>
		<name>nesne</name>
		<occluded>0</occluded>
		<pose>Unspecified</pose>
		<truncated>0</truncated>
		<difficult>0</difficult>
		<polygon>
			<x1>688</x1>
			<y1>296</y1>
			<x2>746</x2>
			<y2>297</y2>
			<x3>746</x3>
			<y3>281</y3>
			<x4>792</x4>
			<y4>282</y4>
			<x5>810</x5>
			<y5>282</y5>
			<x6>841</x6>
			<y6>300</y6>
			<x7>859</x7>
			<y7>300</y7>
			<x8>859</x8>
			<y8>313</y8>
			<x9>685</x9>
			<y9>312</y9>
		</polygon>
		<bndbox>
			<xmin>685</xmin>
			<ymin>281</ymin>
			<xmax>859</xmax>
			<ymax>313</ymax>
		</bndbox>
	</object>
	<object>
		<name>nesne</name>
		<occluded>0</occluded>
		<pose>Unspecified</pose>
		<truncated>0</truncated>
		<difficult>0</difficult>
		<polygon>
			<x1>873</x1>
			<y1>317</y1>
			<x2>872</x2>
			<y2>355</y2>
			<x3>797</x3>
			<y3>353</y3>
			<x4>800</x4>
			<y4>317</y4>
		</polygon>
		<bndbox>
			<xmin>797</xmin>
			<ymin>317</ymin>
			<xmax>873</xmax>
			<ymax>355</ymax>
		</bndbox>
	</object>
	<object>
		<name>nesne</name>
		<occluded>0</occluded>
		<pose>Unspecified</pose>
		<truncated>0</truncated>
		<difficult>0</difficult>
		<polygon>
			<x1>927</x1>
			<y1>317</y1>
			<x2>870</x2>
			<y2>316</y2>
			<x3>870</x3>
			<y3>354</y3>
			<x4>928</x4>
			<y4>355</y4>
		</polygon>
		<bndbox>
			<xmin>870</xmin>
			<ymin>316</ymin>
			<xmax>928</xmax>
			<ymax>355</ymax>
		</bndbox>
	</object>
	<object>
		<name>nesne</name>
		<occluded>0</occluded>
		<pose>Unspecified</pose>
		<truncated>0</truncated>
		<difficult>0</difficult>
		<polygon>
			<x1>928</x1>
			<y1>353</y1>
			<x2>798</x2>
			<y2>354</y2>
			<x3>799</x3>
			<y3>316</y3>
			<x4>928</x4>
			<y4>316</y4>
		</polygon>
		<bndbox>
			<xmin>798</xmin>
			<ymin>316</ymin>
			<xmax>928</xmax>
			<ymax>354</ymax>
		</bndbox>
	</object>
	<object>
		<name>nesne</name>
		<occluded>0</occluded>
		<pose>Unspecified</pose>
		<truncated>0</truncated>
		<difficult>0</difficult>
		<polygon>
			<x1>929</x1>
			<y1>367</y1>
			<x2>593</x2>
			<y2>357</y2>
			<x3>288</x3>
			<y3>343</y3>
			<x4>157</x4>
			<y4>336</y4>
			<x5>149</x5>
			<y5>339</y5>
			<x6>191</x6>
			<y6>343</y6>
			<x7>289</x7>
			<y7>346</y7>
			<x8>447</x8>
			<y8>354</y8>
			<x9>604</x9>
			<y9>362</y9>
			<x10>928</x10>
			<y10>372</y10>
		</polygon>
		<bndbox>
			<xmin>149</xmin>
			<ymin>336</ymin>
			<xmax>929</xmax>
			<ymax>372</ymax>
		</bndbox>
	</object>
	<object>
		<name>nesne</name>
		<occluded>0</occluded>
		<pose>Unspecified</pose>
		<truncated>0</truncated>
		<difficult>0</difficult>
		<polygon>
			<x1>122</x1>
			<y1>355</y1>
			<x2>196</x2>
			<y2>361</y2>
			<x3>190</x3>
			<y3>366</y3>
			<x4>118</x4>
			<y4>361</y4>
		</polygon>
		<bndbox>
			<xmin>118</xmin>
			<ymin>355</ymin>
			<xmax>196</xmax>
			<ymax>366</ymax>
		</bndbox>
	</object>
	<object>
		<name>nesne</name>
		<occluded>0</occluded>
		<pose>Unspecified</pose>
		<truncated>0</truncated>
		<difficult>0</difficult>
		<polygon>
			<x1>81</x1>
			<y1>393</y1>
			<x2>98</x2>
			<y2>395</y2>
			<x3>114</x3>
			<y3>399</y3>
			<x4>118</x4>
			<y4>412</y4>
			<x5>114</x5>
			<y5>420</y5>
			<x6>96</x6>
			<y6>430</y6>
			<x7>1</x7>
			<y7>455</y7>
			<x8>0</x8>
			<y8>461</y8>
			<x9>68</x9>
			<y9>445</y9>
			<x10>119</x10>
			<y10>426</y10>
			<x11>130</x11>
			<y11>416</y11>
			<x12>130</x12>
			<y12>404</y12>
			<x13>118</x13>
			<y13>395</y13>
			<x14>80</x14>
			<y14>386</y14>
		</polygon>
		<bndbox>
			<xmin>0</xmin>
			<ymin>386</ymin>
			<xmax>130</xmax>
			<ymax>461</ymax>
		</bndbox>
	</object>
	<object>
		<name>nesne</name>
		<occluded>0</occluded>
		<pose>Unspecified</pose>
		<truncated>0</truncated>
		<difficult>0</difficult>
		<polygon>
			<x1>58</x1>
			<y1>429</y1>
			<x2>52</x2>
			<y2>416</y2>
			<x3>57</x3>
			<y3>405</y3>
			<x4>56</x4>
			<y4>395</y4>
			<x5>50</x5>
			<y5>383</y5>
			<x6>54</x6>
			<y6>365</y6>
			<x7>60</x7>
			<y7>361</y7>
			<x8>64</x8>
			<y8>367</y8>
			<x9>66</x9>
			<y9>378</y9>
			<x10>70</x10>
			<y10>384</y10>
			<x11>75</x11>
			<y11>390</y11>
			<x12>77</x12>
			<y12>398</y12>
			<x13>84</x13>
			<y13>400</y13>
			<x14>96</x14>
			<y14>411</y14>
			<x15>104</x15>
			<y15>419</y15>
			<x16>101</x16>
			<y16>425</y16>
			<x17>93</x17>
			<y17>423</y17>
			<x18>80</x18>
			<y18>425</y18>
			<x19>69</x19>
			<y19>431</y19>
		</polygon>
		<bndbox>
			<xmin>50</xmin>
			<ymin>361</ymin>
			<xmax>104</xmax>
			<ymax>431</ymax>
		</bndbox>
	</object>
	<object>
		<name>nesne</name>
		<occluded>0</occluded>
		<pose>Unspecified</pose>
		<truncated>0</truncated>
		<difficult>0</difficult>
		<polygon>
			<x1>750</x1>
			<y1>507</y1>
			<x2>745</x2>
			<y2>489</y2>
			<x3>730</x3>
			<y3>493</y3>
			<x4>724</x4>
			<y4>481</y4>
			<x5>719</x5>
			<y5>456</y5>
			<x6>739</x6>
			<y6>453</y6>
			<x7>748</x7>
			<y7>457</y7>
			<x8>763</x8>
			<y8>455</y8>
			<x9>783</x9>
			<y9>461</y9>
			<x10>788</x10>
			<y10>484</y10>
			<x11>783</x11>
			<y11>497</y11>
			<x12>768</x12>
			<y12>506</y12>
			<x13>757</x13>
			<y13>512</y13>
			<x14>748</x14>
			<y14>502</y14>
		</polygon>
		<bndbox>
			<xmin>719</xmin>
			<ymin>453</ymin>
			<xmax>788</xmax>
			<ymax>512</ymax>
		</bndbox>
	</object>
	<object>
		<name>nesne</name>
		<occluded>0</occluded>
		<pose>Unspecified</pose>
		<truncated>0</truncated>
		<difficult>0</difficult>
		<polygon>
			<x1>790</x1>
			<y1>480</y1>
			<x2>801</x2>
			<y2>465</y2>
			<x3>806</x3>
			<y3>464</y3>
			<x4>816</x4>
			<y4>457</y4>
			<x5>829</x5>
			<y5>456</y5>
			<x6>839</x6>
			<y6>452</y6>
			<x7>856</x7>
			<y7>446</y7>
			<x8>854</x8>
			<y8>459</y8>
			<x9>857</x9>
			<y9>465</y9>
			<x10>859</x10>
			<y10>473</y10>
			<x11>848</x11>
			<y11>475</y11>
			<x12>832</x12>
			<y12>482</y12>
			<x13>823</x13>
			<y13>469</y13>
			<x14>817</x14>
			<y14>473</y14>
			<x15>819</x15>
			<y15>480</y15>
			<x16>825</x16>
			<y16>480</y16>
			<x17>833</x17>
			<y17>486</y17>
			<x18>836</x18>
			<y18>490</y18>
			<x19>836</x19>
			<y19>498</y19>
			<x20>836</x20>
			<y20>508</y20>
			<x21>837</x21>
			<y21>512</y21>
			<x22>795</x22>
			<y22>513</y22>
			<x23>783</x23>
			<y23>500</y23>
		</polygon>
		<bndbox>
			<xmin>783</xmin>
			<ymin>446</ymin>
			<xmax>859</xmax>
			<ymax>513</ymax>
		</bndbox>
	</object>
	<object>
		<name>nesne</name>
		<occluded>0</occluded>
		<pose>Unspecified</pose>
		<truncated>0</truncated>
		<difficult>0</difficult>
		<polygon>
			<x1>865</x1>
			<y1>458</y1>
			<x2>893</x2>
			<y2>456</y2>
			<x3>928</x3>
			<y3>455</y3>
			<x4>928</x4>
			<y4>461</y4>
			<x5>877</x5>
			<y5>459</y5>
			<x6>857</x6>
			<y6>466</y6>
			<x7>854</x7>
			<y7>457</y7>
		</polygon>
		<bndbox>
			<xmin>854</xmin>
			<ymin>455</ymin>
			<xmax>928</xmax>
			<ymax>466</ymax>
		</bndbox>
	</object>
	<object>
		<name>nesne</name>
		<occluded>0</occluded>
		<pose>Unspecified</pose>
		<truncated>0</truncated>
		<difficult>0</difficult>
		<polygon>
			<x1>730</x1>
			<y1>389</y1>
			<x2>789</x2>
			<y2>390</y2>
			<x3>791</x3>
			<y3>395</y3>
			<x4>725</x4>
			<y4>395</y4>
			<x5>724</x5>
			<y5>388</y5>
		</polygon>
		<bndbox>
			<xmin>724</xmin>
			<ymin>388</ymin>
			<xmax>791</xmax>
			<ymax>395</ymax>
		</bndbox>
	</object>
	<object>
		<name>nesne</name>
		<occluded>0</occluded>
		<pose>Unspecified</pose>
		<truncated>0</truncated>
		<difficult>0</difficult>
		<polygon>
			<x1>799</x1>
			<y1>392</y1>
			<x2>869</x2>
			<y2>392</y2>
			<x3>867</x3>
			<y3>400</y3>
			<x4>796</x4>
			<y4>398</y4>
		</polygon>
		<bndbox>
			<xmin>796</xmin>
			<ymin>392</ymin>
			<xmax>869</xmax>
			<ymax>400</ymax>
		</bndbox>
	</object>
	<object>
		<name>nesne</name>
		<occluded>0</occluded>
		<pose>Unspecified</pose>
		<truncated>0</truncated>
		<difficult>0</difficult>
		<polygon>
			<x1>596</x1>
			<y1>387</y1>
			<x2>599</x2>
			<y2>384</y2>
			<x3>475</x3>
			<y3>378</y3>
			<x4>475</x4>
			<y4>383</y4>
			<x5>601</x5>
			<y5>388</y5>
		</polygon>
		<bndbox>
			<xmin>475</xmin>
			<ymin>378</ymin>
			<xmax>601</xmax>
			<ymax>388</ymax>
		</bndbox>
	</object>
	<object>
		<name>nesne</name>
		<occluded>0</occluded>
		<pose>Unspecified</pose>
		<truncated>0</truncated>
		<difficult>0</difficult>
		<polygon>
			<x1>272</x1>
			<y1>364</y1>
			<x2>373</x2>
			<y2>369</y2>
			<x3>363</x3>
			<y3>378</y3>
			<x4>264</x4>
			<y4>369</y4>
		</polygon>
		<bndbox>
			<xmin>264</xmin>
			<ymin>364</ymin>
			<xmax>373</xmax>
			<ymax>378</ymax>
		</bndbox>
	</object>
	<object>
		<name>nesne</name>
		<occluded>0</occluded>
		<pose>Unspecified</pose>
		<truncated>0</truncated>
		<difficult>0</difficult>
		<polygon>
			<x1>237</x1>
			<y1>523</y1>
			<x2>302</x2>
			<y2>486</y2>
			<x3>312</x3>
			<y3>490</y3>
			<x4>253</x4>
			<y4>527</y4>
		</polygon>
		<bndbox>
			<xmin>237</xmin>
			<ymin>486</ymin>
			<xmax>312</xmax>
			<ymax>527</ymax>
		</bndbox>
	</object>
	<object>
		<name>nesne</name>
		<occluded>0</occluded>
		<pose>Unspecified</pose>
		<truncated>0</truncated>
		<difficult>0</difficult>
		<polygon>
			<x1>706</x1>
			<y1>525</y1>
			<x2>718</x2>
			<y2>508</y2>
			<x3>721</x3>
			<y3>498</y3>
			<x4>732</x4>
			<y4>495</y4>
			<x5>742</x5>
			<y5>490</y5>
			<x6>746</x6>
			<y6>495</y6>
			<x7>736</x7>
			<y7>507</y7>
			<x8>729</x8>
			<y8>520</y8>
			<x9>726</x9>
			<y9>525</y9>
		</polygon>
		<bndbox>
			<xmin>706</xmin>
			<ymin>490</ymin>
			<xmax>746</xmax>
			<ymax>525</ymax>
		</bndbox>
	</object>
	<object>
		<name>nesne</name>
		<occluded>0</occluded>
		<pose>Unspecified</pose>
		<truncated>0</truncated>
		<difficult>0</difficult>
		<polygon>
			<x1>233</x1>
			<y1>526</y1>
			<x2>304</x2>
			<y2>484</y2>
			<x3>477</x3>
			<y3>377</y3>
			<x4>601</x4>
			<y4>381</y4>
			<x5>772</x5>
			<y5>390</y5>
			<x6>871</x6>
			<y6>391</y6>
			<x7>928</x7>
			<y7>392</y7>
			<x8>928</x8>
			<y8>456</y8>
			<x9>857</x9>
			<y9>458</y9>
			<x10>856</x10>
			<y10>445</y10>
			<x11>823</x11>
			<y11>458</y11>
			<x12>799</x12>
			<y12>462</y12>
			<x13>791</x13>
			<y13>480</y13>
			<x14>786</x14>
			<y14>476</y14>
			<x15>777</x15>
			<y15>459</y15>
			<x16>757</x16>
			<y16>455</y16>
			<x17>749</x17>
			<y17>457</y17>
			<x18>736</x18>
			<y18>452</y18>
			<x19>721</x19>
			<y19>457</y19>
			<x20>721</x20>
			<y20>475</y20>
			<x21>729</x21>
			<y21>492</y21>
			<x22>722</x22>
			<y22>498</y22>
			<x23>715</x23>
			<y23>515</y23>
			<x24>703</x24>
			<y24>524</y24>
		</polygon>
		<bndbox>
			<xmin>233</xmin>
			<ymin>377</ymin>
			<xmax>928</xmax>
			<ymax>526</ymax>
		</bndbox>
	</object>
	<object>
		<name>nesne</name>
		<occluded>0</occluded>
		<pose>Unspecified</pose>
		<truncated>0</truncated>
		<difficult>0</difficult>
		<polygon>
			<x1>3</x1>
			<y1>378</y1>
			<x2>51</x2>
			<y2>385</y2>
			<x3>52</x3>
			<y3>389</y3>
			<x4>2</x4>
			<y4>384</y4>
		</polygon>
		<bndbox>
			<xmin>2</xmin>
			<ymin>378</ymin>
			<xmax>52</xmax>
			<ymax>389</ymax>
		</bndbox>
	</object>
	<object>
		<name>nesne</name>
		<occluded>0</occluded>
		<pose>Unspecified</pose>
		<truncated>0</truncated>
		<difficult>0</difficult>
		<polygon>
			<x1>1</x1>
			<y1>344</y1>
			<x2>28</x2>
			<y2>347</y2>
			<x3>31</x3>
			<y3>351</y3>
			<x4>0</x4>
			<y4>349</y4>
		</polygon>
		<bndbox>
			<xmin>0</xmin>
			<ymin>344</ymin>
			<xmax>31</xmax>
			<ymax>351</ymax>
		</bndbox>
	</object>
	<object>
		<name>nesne</name>
		<occluded>0</occluded>
		<pose>Unspecified</pose>
		<truncated>0</truncated>
		<difficult>0</difficult>
		<polygon>
			<x1>0</x1>
			<y1>470</y1>
			<x2>0</x2>
			<y2>453</y2>
			<x3>96</x3>
			<y3>426</y3>
			<x4>116</x4>
			<y4>418</y4>
			<x5>115</x5>
			<y5>399</y5>
			<x6>79</x6>
			<y6>390</y6>
			<x7>73</x7>
			<y7>392</y7>
			<x8>60</x8>
			<y8>360</y8>
			<x9>51</x9>
			<y9>365</y9>
			<x10>53</x10>
			<y10>387</y10>
			<x11>0</x11>
			<y11>382</y11>
			<x12>2</x12>
			<y12>341</y12>
			<x13>31</x13>
			<y13>346</y13>
			<x14>35</x14>
			<y14>327</y14>
			<x15>39</x15>
			<y15>349</y15>
			<x16>49</x16>
			<y16>347</y16>
			<x17>61</x17>
			<y17>350</y17>
			<x18>65</x18>
			<y18>326</y18>
			<x19>68</x19>
			<y19>326</y19>
			<x20>71</x20>
			<y20>346</y20>
			<x21>79</x21>
			<y21>351</y21>
			<x22>95</x22>
			<y22>347</y22>
			<x23>127</x23>
			<y23>350</y23>
			<x24>276</x24>
			<y24>360</y24>
			<x25>475</x25>
			<y25>374</y25>
			<x26>310</x26>
			<y26>490</y26>
			<x27>267</x27>
			<y27>523</y27>
			<x28>0</x28>
			<y28>524</y28>
		</polygon>
		<bndbox>
			<xmin>0</xmin>
			<ymin>328</ymin>
			<xmax>475</xmax>
			<ymax>515</ymax>
		</bndbox>
	</object>
	<object>
		<name>nesne</name>
		<occluded>0</occluded>
		<pose>Unspecified</pose>
		<truncated>0</truncated>
		<difficult>0</difficult>
		<polygon>
			<x1>724</x1>
			<y1>526</y1>
			<x2>744</x2>
			<y2>493</y2>
			<x3>758</x3>
			<y3>511</y3>
			<x4>783</x4>
			<y4>497</y4>
			<x5>796</x5>
			<y5>512</y5>
			<x6>839</x6>
			<y6>511</y6>
			<x7>831</x7>
			<y7>481</y7>
			<x8>816</x8>
			<y8>474</y8>
			<x9>822</x9>
			<y9>469</y9>
			<x10>831</x10>
			<y10>476</y10>
			<x11>855</x11>
			<y11>472</y11>
			<x12>860</x12>
			<y12>465</y12>
			<x13>861</x13>
			<y13>460</y13>
			<x14>885</x14>
			<y14>458</y14>
			<x15>930</x15>
			<y15>456</y15>
			<x16>930</x16>
			<y16>361</y16>
			<x17>163</x17>
			<y17>332</y17>
			<x18>152</x18>
			<y18>339</y18>
			<x19>143</x19>
			<y19>333</y19>
			<x20>132</x20>
			<y20>343</y20>
			<x21>128</x21>
			<y21>332</y21>
			<x22>96</x22>
			<y22>335</y22>
			<x23>95</x23>
			<y23>348</y23>
			<x24>74</x24>
			<y24>351</y24>
			<x25>68</x25>
			<y25>326</y25>
			<x26>66</x26>
			<y26>349</y26>
			<x27>49</x27>
			<y27>344</y27>
			<x28>40</x28>
			<y28>350</y28>
			<x29>38</x29>
			<y29>325</y29>
			<x30>34</x30>
			<y30>344</y30>
			<x31>2</x31>
			<y31>341</y31>
			<x32>0</x32>
			<y32>379</y32>
			<x33>53</x33>
			<y33>388</y33>
			<x34>53</x34>
			<y34>364</y34>
			<x35>57</x35>
			<y35>360</y35>
			<x36>72</x36>
			<y36>389</y36>
			<x37>97</x37>
			<y37>397</y37>
			<x38>114</x38>
			<y38>397</y38>
			<x39>115</x39>
			<y39>408</y39>
			<x40>111</x40>
			<y40>420</y40>
			<x41>2</x41>
			<y41>453</y41>
			<x42>0</x42>
			<y42>526</y42>
		</polygon>
		<bndbox>
			<xmin>0</xmin>
			<ymin>328</ymin>
			<xmax>930</xmax>
			<ymax>529</ymax>
		</bndbox>
	</object>
</annotation>
